odkutils/__init__.py
odkutils/caj2pdf/__init__.py
odkutils/caj2pdf/cajparser.py
odkutils/caj2pdf/HNParsePage.py
odkutils/caj2pdf/jbig2dec.py
odkutils/caj2pdf/jbigdec.py
odkutils/caj2pdf/lib/bin/libjbig2codec-w32.dll
odkutils/caj2pdf/lib/bin/libjbig2codec-w64.dll
odkutils/caj2pdf/lib/bin/libjbigdec-w32.dll
odkutils/caj2pdf/lib/bin/libjbigdec-w64.dll
odkutils/caj2pdf/lib/decode_jbig2data.cc
odkutils/caj2pdf/lib/decode_jbig2data_x.cc
odkutils/caj2pdf/lib/jbigdec.cc
odkutils/caj2pdf/lib/JBigDecode.cc
odkutils/caj2pdf/lib/JBigDecode.h
odkutils/caj2pdf/pdfwutils.py
odkutils/caj2pdf/utils.py
odkutils/exmath.py
odkutils/imgutils.py
odkutils/mlutils.py
odkutils/odkipfs.py
odkutils/utils.py
odkutils-0.2.2.dist-info/METADATA
odkutils-0.2.2.dist-info/WHEEL
odkutils-0.2.2.dist-info/RECORD
