Metadata-Version: 2.3
Name: odkutils
Version: 0.2.2
Summary: ODK工具箱
License: MIT
Author: oldking.club
Requires-Python: >=3.11
Classifier: License :: OSI Approved :: MIT License
Classifier: Programming Language :: Python :: 3
Classifier: Programming Language :: Python :: 3.11
Classifier: Programming Language :: Python :: 3.12
Classifier: Programming Language :: Python :: 3.13
Requires-Dist: tqdm (>=4.67.1,<5.0.0)
